JTrainer/Trainer.py
JTrainer/__init__.py
JTrainer-1.0.0.dist-info/METADATA
JTrainer-1.0.0.dist-info/WHEEL
JTrainer-1.0.0.dist-info/license.txt
JTrainer-1.0.0.dist-info/top_level.txt
JTrainer-1.0.0.dist-info/RECORD
